dwdat2py/DWDataReaderHeader.py
dwdat2py/__init__.py
dwdat2py/wrappers.py
dwdat2py/libs/DWDataReaderLib.dll
dwdat2py/libs/DWDataReaderLib.so
dwdat2py/libs/DWDataReaderLib64.dll
dwdat2py/libs/DWDataReaderLib64.so
dwdat2py/libs/DWDataReaderv.doc.txt
dwdat2py-0.3.3.dist-info/LICENSE.txt
dwdat2py-0.3.3.dist-info/METADATA
dwdat2py-0.3.3.dist-info/WHEEL
dwdat2py-0.3.3.dist-info/top_level.txt
dwdat2py-0.3.3.dist-info/RECORD
