Metadata-Version: 2.1
Name: dwdat2py
Version: 0.3.3
Summary: Python wrappers around functions in Dewesoft DWDataReaderLib shared library
Home-page: https://github.com/tomnor/dwdat2py
Author: Tomas Nordin
Author-email: tomasn@posteo.net
License: Apache 2.0
Download-URL: https://github.com/tomnor/dwdat/tarball/master
Platform: UNKNOWN
Classifier: Intended Audience :: Science/Research
Classifier: License :: OSI Approved :: Apache Software License
Classifier: Topic :: Scientific/Engineering :: Information Analysis
Classifier: Topic :: Scientific/Engineering :: Visualization
Classifier: Programming Language :: Python :: 3
Classifier: Operating System :: POSIX :: Linux
Classifier: Operating System :: Microsoft :: Windows
Classifier: Development Status :: 3 - Alpha
